nonebot_plugin_mmm/__init__.py
nonebot_plugin_mmm-0.2.3.dist-info/LICENSE
nonebot_plugin_mmm-0.2.3.dist-info/METADATA
nonebot_plugin_mmm-0.2.3.dist-info/WHEEL
nonebot_plugin_mmm-0.2.3.dist-info/RECORD
